LICENSE
README.md
setup.py
nonebot_plugin_jingdong/__init__.py
nonebot_plugin_jingdong/data_source.py
nonebot_plugin_jingdong.egg-info/PKG-INFO
nonebot_plugin_jingdong.egg-info/SOURCES.txt
nonebot_plugin_jingdong.egg-info/dependency_links.txt
nonebot_plugin_jingdong.egg-info/requires.txt
nonebot_plugin_jingdong.egg-info/top_level.txt