Metadata-Version: 2.1
Name: nonebot-plugin-jingdong
Version: 0.0.1
Summary: 基于NoneBot2的京东查询插件
Home-page: https://github.com/17TheWord/nonebot-plugin-jingdong
Author: 17TheWord
Author-email: 17theword@gmail.com
License: UNKNOWN
Project-URL: Bug Tracker, https://github.com/17TheWord/nonebot-plugin-jingdong
Platform: UNKNOWN
Classifier: Programming Language :: Python :: 3
Classifier: License :: OSI Approved :: MIT License
Classifier: Operating System :: OS Independent
Requires-Python: >=3.8
License-File: LICENSE
